autoeagle/__init__.py
autoeagle/autoeagle.toml
autoeagle/autoeagle_config.py
autoeagle/core.py
autoeagle/ulp_generator.py
autoeagle/ulp_script_template.txt
autoeagle/ulp_template.txt
autoeagle-1.0.1.dist-info/METADATA
autoeagle-1.0.1.dist-info/WHEEL
autoeagle-1.0.1.dist-info/entry_points.txt
autoeagle-1.0.1.dist-info/licenses/LICENSE.txt
autoeagle-1.0.1.dist-info/RECORD
