Metadata-Version: 2.1
Name: autoeagle
Version: 1.0.1
Summary: Automate tasks in Autodesk's Eagle software by invoking Python scripts from the program's command line.
Project-URL: Homepage, https://github.com/matt-manes/autoeagle
Project-URL: Documentation, https://github.com/matt-manes/autoeagle/tree/main/docs
Project-URL: Source code, https://github.com/matt-manes/autoeagle/tree/main/src/autoeagle
Author-email: Matt Manes <mattmanes@pm.me>
License-File: LICENSE.txt
Keywords: automation,cad,eagle,pcb
Classifier: License :: OSI Approved :: MIT License
Classifier: Operating System :: OS Independent
Classifier: Programming Language :: Python :: 3
Requires-Python: >=3.6
Requires-Dist: pytest
Requires-Dist: tomlkit
